Section 2/miniUART/transmitter.v
// A simple transmiter from a UART
module transmitter(
    input [7:0] byte,
    input start_transfert,
    input clock,
    output reg serial_output
);

reg idle = 1'b1;
reg start_bit = 1'b1;
reg [7:0] bit_counter = 0;
reg transmit = 1'b0;

always @ (posedge clock && idle) begin
    serial_output = 1'b1;
    start_bit = 1'b1;
end

always @ (posedge clock && transmit) begin
    if (start_bit) begin
        serial_output = 1'b0;
        idle = 1'b0;
        start_bit = 1'b0;
    end else begin
        if (bit_counter < 7) begin
            serial_output = byte[bit_counter];
            bit_counter <= bit_counter + 1;
        end else begin
            idle = 1'b1;
            transmit = 1'b0;
            bit_counter = 0;
        end
        
    end
end

always @ (posedge start_transfert) transmit = 1'b1;

endmodule

Section 2/miniUART/transmitter_tb.v
// // A transmitter from a UART
`include "transmitter.v"

module transmitter_tb();
reg [7:0] byte = 3;
reg clock;
reg start_transfert;

transmitter TX (
    byte,
    start_transfert,
    clock,
    serial_output
);

initial begin
    $monitor("CLOCK: %b\tbyte=%g  => output = %b", clock, byte, serial_output);
    $dumpfile("transmitter.vcd");
    $dumpvars(0, TX);
    start_transfert = 0;
    clock = 1;

    #10 start_transfert <= 1'b1;
    #1 start_transfert <= 1'b0;

    #30 $finish;
end

always  #1  clock = ~clock;

endmodule

Section 2/miniUART/transmitter.vcd
$date
	Fri Apr 17 22:56:47 2020
$end
$version
	Icarus Verilog
$end
$timescale
	1s
$end
$scope module transmitter_tb $end
$scope module TX $end
$var wire 8 ! byte [7:0] $end
$var wire 1 " clock $end
$var wire 1 # start_transfert $end
$var reg 8 $ bit_counter [7:0] $end
$var reg 1 % idle $end
$var reg 1 & serial_output $end
$var reg 1 ' start_bit $end
$var reg 1 ( transmit $end
$upscope $end
$upscope $end
$enddefinitions $end
#0
$dumpvars
0(
1'
1&
1%
b0 $
0#
1"
b11 !
$end
#1
0"
#2
1"
#3
0"
#4
1"
#5
0"
#6
1"
#7
0"
#8
1"
#9
0"
#10
0'
0%
0&
1(
1#
1"
#11
0#
0"
#12
b1 $
1&
1"
#13
0"
#14
b10 $
1"
#15
0"
#16
b11 $
0&
1"
#17
0"
#18
b100 $
1"
#19
0"
#20
b101 $
1"
#21
0"
#22
b110 $
1"
#23
0"
#24
b111 $
1"
#25
0"
#26
1'
1&
b0 $
0(
1%
1"
