Section 2/miniUART/receiver.v
// A simple receiver from a UART
module receiver(
    input stream,
    input clock,
    output reg [7:0] byte
);

reg [3:0] bit_counter;
reg record = 1'b0;

always @ (posedge clock && record) #1 begin
    byte[bit_counter] <= stream;
    bit_counter <= bit_counter + 1;
    if (bit_counter > 7) begin
        bit_counter = 0;
        record = 1'b0;
    end
end

always @ (negedge stream && (record == 1'b0)) #1 begin
    record = 1'b1;
    byte = 0;
    bit_counter = 0;
end

endmodule

Section 2/miniUART/transmitter.v
// A simple transmiter from a UART
module transmitter(
    input [7:0] byte,
    input start_transfert,
    input clock,
    output reg serial_output
);

reg idle_mode = 1'b1;
reg transmit_mode = 1'b0;

reg start_bit = 1'b1;
reg [4:0] bit_counter = 0;


always @ (posedge clock && idle_mode) begin
    serial_output = 1'b1;
    start_bit = 1'b1;
    bit_counter = 0;
end

always @ (posedge clock && transmit_mode) begin
    if (start_bit) begin
        serial_output = 1'b0;
        idle_mode = 1'b0;
        start_bit = 1'b0;
        bit_counter = 0;
    end else begin
        if (bit_counter < 8) begin
            serial_output = byte[bit_counter];
            bit_counter = bit_counter + 1;
        end else begin
            idle_mode = 1'b1;
            transmit_mode = 1'b0;
            bit_counter = 0;
        end
        
    end
end

always @ (posedge start_transfert) transmit_mode = 1'b1;

endmodule

Section 2/miniUART/uart_tb.v
// UART test-bench
`include "transmitter.v"
`include "receiver.v"

module uart_tb();
reg [7:0] tx_byte = 230;
reg clock;
reg start_transfert;

wire [7:0] rx_byte;

transmitter TX (
    tx_byte,
    start_transfert,
    clock,
    serial_output
);

receiver RX (
    serial_output,
    clock,
    rx_byte
);

initial begin
    $monitor("CLOCK: %b\tbyte=%g  => output = %b", clock, tx_byte, serial_output);
    $dumpfile("uart.vcd");
    $dumpvars(0, uart_tb);
    start_transfert = 0;
    clock = 1;

    #10 start_transfert <= 1'b1;
    #1 start_transfert <= 1'b0;

    #30 $finish;
end

always  #1  clock = ~clock;

endmodule

Section 2/miniUART/uart.vcd
$date
	Sat Apr 18 12:18:32 2020
$end
$version
	Icarus Verilog
$end
$timescale
	1s
$end
$scope module uart_tb $end
$var wire 1 ! serial_output $end
$var wire 8 " rx_byte [7:0] $end
$var reg 1 # clock $end
$var reg 1 $ start_transfert $end
$var reg 8 % tx_byte [7:0] $end
$scope module RX $end
$var wire 1 # clock $end
$var wire 1 ! stream $end
$var reg 4 & bit_counter [3:0] $end
$var reg 8 ' byte [7:0] $end
$var reg 1 ( record $end
$upscope $end
$scope module TX $end
$var wire 8 ) byte [7:0] $end
$var wire 1 # clock $end
$var wire 1 $ start_transfert $end
$var reg 5 * bit_counter [4:0] $end
$var reg 1 + idle_mode $end
$var reg 1 ! serial_output $end
$var reg 1 , start_bit $end
$var reg 1 - transmit_mode $end
$upscope $end
$upscope $end
$enddefinitions $end
#0
$dumpvars
0-
1,
1+
b0 *
b11100110 )
0(
bx '
bx &
b11100110 %
0$
1#
bx "
1!
$end
#1
0#
#2
1#
#3
0#
#4
1#
#5
0#
#6
1#
#7
0#
#8
1#
#9
0#
#10
0,
0+
0!
1-
1$
1#
#11
0$
b0 &
b0 "
b0 '
1(
0#
#12
b1 *
1#
#13
b1 &
0#
#14
b10 *
1!
1#
#15
b10 &
b10 "
b10 '
0#
#16
b11 *
1#
#17
b11 &
b110 "
b110 '
0#
#18
b100 *
0!
1#
#19
b100 &
0#
#20
b101 *
1#
#21
b101 &
0#
#22
b110 *
1!
1#
#23
b110 &
b100110 "
b100110 '
0#
#24
b111 *
1#
#25
b111 &
b1100110 "
b1100110 '
0#
#26
b1000 *
1#
#27
b1000 &
b11100110 "
b11100110 '
0#
#28
1,
b0 *
0-
1+
1#
#29
0(
b1001 &
0#
