Section 2/LED_blinker.v
// A simple LED blinker module

module LED_blinker(
    input clock, // clock input of the design
    input reset, // reset input
    output LED // output for the LED
);

reg LED;
wire clock, reset;

always @ (posedge clock or posedge reset) begin
    if (reset == 1'b1) begin
        LED = 1;
    end
    LED = ~LED;
end

endmodule

Section 2/LED_blinker_tb.v
// LED blinker test-bench
`include "LED_blinker.v"

module LED_blinker_tb();
reg clock;
reg reset;
wire LED;

// Initialization
initial begin
    $monitor("%g\t clock=%b, reset=%b, LED=%b", $time, clock, reset, LED);
    $dumpfile("LED_blinker.vcd");
    $dumpvars(0, LED_b);
    clock = 1; // initial value of clock
    #2 reset = 1; // We wait 2 tick then we reset the blinking
    #2 reset = 0;
    #13 reset = 1;
    #15 reset = 0;
    #50 $finish;
end

// Clock generator
always #2 clock = ~clock;

LED_blinker LED_b(
    clock,
    reset,
    LED
);

endmodule

Section 2/LED_blinker/LED_blinker.vcd
$date
	Tue Apr 14 13:02:56 2020
$end
$version
	Icarus Verilog
$end
$timescale
	1s
$end
$scope module LED_blinker_tb $end
$scope module LED_b $end
$var wire 1 ! clock $end
$var wire 1 " reset $end
$var reg 1 # LED $end
$upscope $end
$upscope $end
$enddefinitions $end
#0
$dumpvars
x#
x"
1!
$end
#2
0#
0!
1"
#4
1#
1!
0"
#6
0!
#8
0#
1!
#10
0!
#12
1#
1!
#14
0!
#16
0#
1!
#17
0#
1"
#18
0!
#20
0#
1!
#22
0!
#24
0#
1!
#26
0!
#28
0#
1!
#30
0!
#32
1#
1!
0"
#34
0!
#36
0#
1!
#38
0!
#40
1#
1!
#42
0!
#44
0#
1!
#46
0!
#48
1#
1!
#50
0!
#52
0#
1!
#54
0!
#56
1#
1!
#58
0!
#60
0#
1!
#62
0!
#64
1#
1!
#66
0!
#68
0#
1!
#70
0!
#72
1#
1!
#74
0!
#76
0#
1!
#78
0!
#80
1#
1!
