Section 1/arbitrer.v
module arbiter (
clock, 
reset, 
req_0,
req_1, 
gnt_0,
gnt_1
);

input clock, reset, req_0, req_1;
output gnt_0, gnt_1;

reg gnt_0, gnt_1;

always @ (posedge clock or posedge reset)
if (reset) begin
 gnt_0 <= 0;
 gnt_1 <= 0;
end else if (req_0) begin
  gnt_0 <= 1;
  gnt_1 <= 0;
end else if (req_1) begin
  gnt_0 <= 0;
  gnt_1 <= 1;
end

endmodule
// Testbench Code Goes here
module arbiter_tb;

reg clock, reset, req0,req1;
wire gnt0,gnt1;

initial begin
  $monitor ("req0=%b,req1=%b,gnt0=%b,gnt1=%b", req0,req1,gnt0,gnt1);
  $dumpfile("arbitrer.vcd");
  $dumpvars(0, arbiter_tb);
  clock = 0;
  reset = 0;
  req0 = 0;
  req1 = 0;
  #5 reset = 1;
  #15 reset = 0;
  #10 req0 = 1;
  #10 req0 = 0;
  #10 req1 = 1;
  #10 req1 = 0;
  #10 {req0,req1} = 2'b11;
  #10 {req0,req1} = 2'b00;
  #10 $finish;
end

always begin
 #5 clock = !clock;
end

arbiter U0 (
.clock (clock),
.reset (reset),
.req_0 (req0),
.req_1 (req1),
.gnt_0 (gnt0),
.gnt_1 (gnt1)
);

endmodule

Section 1/arbitrer.vcd
$date
	Mon Apr 13 14:48:34 2020
$end
$version
	Icarus Verilog
$end
$timescale
	1s
$end
$scope module arbiter_tb $end
$var wire 1 ! gnt1 $end
$var wire 1 " gnt0 $end
$var reg 1 # clock $end
$var reg 1 $ req0 $end
$var reg 1 % req1 $end
$var reg 1 & reset $end
$scope module U0 $end
$var wire 1 # clock $end
$var wire 1 $ req_0 $end
$var wire 1 % req_1 $end
$var wire 1 & reset $end
$var reg 1 " gnt_0 $end
$var reg 1 ! gnt_1 $end
$upscope $end
$upscope $end
$enddefinitions $end
#0
$dumpvars
0&
0%
0$
0#
x"
x!
$end
#5
0!
0"
1#
1&
#10
0#
#15
1#
#20
0#
0&
#25
1#
#30
0#
1$
#35
1"
1#
#40
0#
0$
#45
1#
#50
0#
1%
#55
1!
0"
1#
#60
0#
0%
#65
1#
#70
0#
1$
1%
#75
0!
1"
1#
#80
0#
0$
0%
